<item>
<title>[COLOR blue][B]===================[/B][/COLOR]</title>
<link>ignora</link>
<thumbnail>https://raw.githubusercontent.com/hackingman/SevyX/master/img/icon.png</thumbnail>
<fanart>https://raw.githubusercontent.com/hackingman/SevyX/master/img/fanart.jpg</fanart>
<externallink></externallink>
</item>
<item>
<title>[B][COLOR blue]::: [COLOR yellow]Sevy[COLOR red]X [COLOR white] - TV LIVE [COLOR blue] :::[/COLOR][/B]</title>
<link>ignora</link>
<thumbnail>https://raw.githubusercontent.com/hackingman/SevyX/master/img/icon.png</thumbnail>
<fanart>https://raw.githubusercontent.com/hackingman/SevyX/master/img/fanart.jpg</fanart>
<externallink></externallink>
</item>
<item>
<title>[COLOR blue][B]===================[/B][/COLOR]</title>
<link>ignora</link>
<thumbnail>https://raw.githubusercontent.com/hackingman/SevyX/master/img/icon.png</thumbnail>
<fanart>https://raw.githubusercontent.com/hackingman/SevyX/master/img/fanart.jpg</fanart>
<externallink></externallink>
</item>

<item>
<title>[COLOR blue][B]==== DIGITALE TERRESTRE ====[/B][/COLOR]</title>
<link>ignora</link>
<thumbnail>https://raw.githubusercontent.com/hackingman/SevyX/master/img/icon.png</thumbnail>
<fanart>https://raw.githubusercontent.com/hackingman/SevyX/master/img/fanart.jpg</fanart>
<externallink>https://raw.githubusercontent.com/hackingman/SevyX/master/tv-live/digitale-terrestre.xml</externallink>
</item>
